up_lpg-0.1.2.dist-info/METADATA
up_lpg-0.1.2.dist-info/RECORD
up_lpg-0.1.2.dist-info/top_level.txt
up_lpg-0.1.2.dist-info/WHEEL
up_lpg-0.1.2.dist-info/LICENSE
up_lpg/lpg
up_lpg/lpg_planner.py
up_lpg/__init__.py
up_lpg-0.1.2.data/data/platlib/lpg
