Metadata-Version: 2.1
Name: up_lpg
Version: 0.1.2
Summary: up_lpg
Author: UNIBS Team
Author-email: ivan.serina@unibs.it
License: APACHE
License-File: LICENSE
